ncall/__init__.py
ncall/_modidx.py
ncall/core.py
ncall/nops.py
ncall/npop.py
ncall-0.0.3.dist-info/LICENSE
ncall-0.0.3.dist-info/METADATA
ncall-0.0.3.dist-info/WHEEL
ncall-0.0.3.dist-info/entry_points.txt
ncall-0.0.3.dist-info/top_level.txt
ncall-0.0.3.dist-info/RECORD
