Metadata-Version: 2.1
Name: ncall
Version: 0.0.3
Summary: ncall
Home-page: https://github.com/dsm-72/ncall
Author: dsm-72
Author-email: sumner.magruder@yale.edu
License: Apache Software License 2.0
Keywords: named callable ncall syn alias fuzzy string matching nym str fuz fuzstr nymstr atyp ispec indoc dynattr
Classifier: Development Status :: 4 - Beta
Classifier: Intended Audience :: Developers
Classifier: Natural Language :: English
Classifier: Programming Language :: Python :: 3.11
Classifier: License :: OSI Approved :: Apache Software License
Requires-Python: >=3.11
License-File: LICENSE
Requires-Dist: atyp
Requires-Dist: regsyn
Requires-Dist: indoc
Requires-Dist: ispec
Requires-Dist: pstr
Requires-Dist: aspec
Requires-Dist: fuzstr
Requires-Dist: nymstr
Requires-Dist: synset
Provides-Extra: dev
